README.md
setup.cfg
setup.py
bin/cansetup
evtgateway.egg-info/PKG-INFO
evtgateway.egg-info/SOURCES.txt
evtgateway.egg-info/dependency_links.txt
evtgateway.egg-info/entry_points.txt
evtgateway.egg-info/not-zip-safe
evtgateway.egg-info/top_level.txt
gateway/__init__.py
gateway/command.py
gateway/exec.py
gateway/launcher.py
gateway/can/__init__.py
gateway/can/configuration.py
gateway/can/engine.py
gateway/can/control/__init__.py
gateway/can/control/errorhandler.py
gateway/can/control/errors.py
gateway/can/control/matcher.py
gateway/can/control/noticehandler.py
gateway/can/control/notices.py
gateway/can/controllers/__init__.py
gateway/can/controllers/base.py
gateway/can/controllers/error.py
gateway/can/controllers/internal.py
gateway/can/traffic/__init__.py
gateway/can/traffic/canout.py
gateway/can/traffic/message.py
gateway/can/traffic/reciever.py
gateway/can/traffic/server.py
gateway/commands/__init__.py
gateway/commands/app.py
gateway/commands/server.py
gateway/commands/start.py
gateway/commands/test.py
gateway/config/canEngine/configuration.json
gateway/core/__init__.py
gateway/core/application.py
gateway/core/provider.py
gateway/core/server.py
gateway/core/service.py
gateway/evtcan/__init__.py
gateway/evtcan/device_construct.py
gateway/evtcan/matcher.py
gateway/launchers/__init__.py
gateway/launchers/controlerize.py
gateway/launchers/initializer.py
gateway/templates/__init__.py
gateway/templates/launcher.py
gateway/utils/__init__.py
gateway/utils/creator.py
gateway/utils/gatewaycommand.py
gateway/utils/resourcelocator.py
gateway/utils/testfinder.py