Metadata-Version: 1.0
Name: evtgateway
Version: 0.4.2
Summary: Gateway for RIT REV1 Sport Bike
Home-page: https://bitbucket.org/evt/gateway-applications
Author: EVT RIT
Author-email: EVT@RIT.EDU
License: MIT
Platform: UNKNOWN
